schema_cntl/__init__.py
schema_cntl/main.py
schema_cntl/schema.py
schema_cntl/settings.py
schema_cntl/dialects/__init__.py
schema_cntl/dialects/postgres.py
schema_cntl/util/__init__.py
schema_cntl/util/logger.py
schema_cntl-1.0.1.dist-info/LICENSE
schema_cntl-1.0.1.dist-info/METADATA
schema_cntl-1.0.1.dist-info/WHEEL
schema_cntl-1.0.1.dist-info/entry_points.txt
schema_cntl-1.0.1.dist-info/top_level.txt
schema_cntl-1.0.1.dist-info/RECORD
