Metadata-Version: 2.1
Name: schema-cntl
Version: 1.0.1
Summary: a schema version control system
Home-page: https://innolab-coverage.makpar-innovation.net
Author: Makpar Innovation Lab
Author-email: gmoore@makpar.com
License: GNU GPL v3
Project-URL: Source, https://github.com/Makpar-Innovation-Laboratory/schema-cntl
Keywords: aws,qldb,quantum-ledger-database,schema,version-control
Platform: any
Requires-Python: >=3.8
License-File: LICENSE
Requires-Dist: innoldb (>=1.0.15)
Requires-Dist: psycopg2-binary (>=2.9.3)
Requires-Dist: python-dotenv (>=0.19.2)
